cn(mg)/COLOCVIU/CN_253_Nicoi_Alexandru_2021_Colocviu_s2/CN_253_Nicoi_Alexandru_2021_Colocviu_s2.v
module Encoder(in, out);
    
    input[6:0] in;
    output[3:0] out;
    reg[3:0] out; 

    always@(in)
    begin
        case(in)
            7'b1111110 : out = 4'b0000;
            7'b0110000 : out = 4'b0001;
            7'b1101101 : out = 4'b0010;
            7'b1111001 : out = 4'b0011;
            7'b0110011 : out = 4'b0100;
            7'b1011011 : out = 4'b0101;
            7'b1011111 : out = 4'b0110;
            7'b1110000 : out = 4'b0111;
            7'b1111111 : out = 4'b1000;
            7'b1110011 : out = 4'b1001; // in tabelul din examen, pentru outputul 9, reprezentarea in 7 biti este de la 3.
                                        // 1110011 afiseaza corect 9, conform vcd.
        endcase    
    end

endmodule

module Testbench;

    reg[6:0] A;
    wire[3:0] Display;

    initial begin
        $dumpfile("subiectul2.vcd");
        $dumpvars;

        A = 7'b1111110;
        
        #10 A = 7'b0110000;
        #10 A = 7'b1101101;
        #10 A = 7'b1111001;

        #10 A = 7'b0110011;
        #10 A = 7'b1011011;
        #10 A = 7'b1011111;
        
        #10 A = 7'b1110000;
        #10 A = 7'b1111111;
        #10 A = 7'b1110011;
        
        #10 $finish;
    end

    initial begin
        $monitor("Input 7 biti: %b, Output 4 biti: %b", A, Display);
    end

    Encoder encoder(A, Display);

endmodule

cn(mg)/COLOCVIU/subiectul2.vcd
$date
	Thu Jun 03 15:36:18 2021
$end
$version
	Icarus Verilog
$end
$timescale
	1s
$end
$scope module Testbench $end
$var wire 4 ! Display [3:0] $end
$var reg 7 " A [6:0] $end
$scope module encoder $end
$var wire 7 # in [6:0] $end
$var reg 4 $ out [3:0] $end
$upscope $end
$upscope $end
$enddefinitions $end
#0
$dumpvars
b0 $
b1111110 #
b1111110 "
b0 !
$end
#10
b1 !
b1 $
b110000 "
b110000 #
#20
b10 !
b10 $
b1101101 "
b1101101 #
#30
b11 !
b11 $
b1111001 "
b1111001 #
#40
b100 !
b100 $
b110011 "
b110011 #
#50
b101 !
b101 $
b1011011 "
b1011011 #
#60
b110 !
b110 $
b1011111 "
b1011111 #
#70
b111 !
b111 $
b1110000 "
b1110000 #
#80
b1000 !
b1000 $
b1111111 "
b1111111 #
#90
b1001 !
b1001 $
b1110011 "
b1110011 #
