cn(mg)/TEMA LAB4/BeCounter.v
/*
Tema Laborator 4

Implementati testbentch pentru modulul behavioral cu 4 biti.
Implementati doar numararea ascendenta sau descendenta si incarcati fisierul v si fisierul VCD.
*/

module BeCounter(out,clk,rst,ld,up,d);
    output [3:0] out;
    input [3:0] d;
    input clk, rst, ld, up;
    reg[3:0] cnt;

    always @(posedge clk) begin
        if (rst)
            cnt <= 4'b0000;
        else if (ld)
            cnt = d;
        else if (up)
            cnt = cnt+1;
        else
            cnt = cnt-1;
    end
    assign out = cnt;
endmodule


module BeCounter_tb;
    reg [3:0] d;
    wire [3:0] out;
    reg clk; 
    reg rst;
    reg ld;
    reg up;

    initial begin
        $dumpfile("BeCounter.VCD");
        $dumpvars;
        clk=0;
        rst=0;
        ld=0;
        up=1;
        #10 rst=1;
        #20 rst=0;
        #20 rst=1;
        #10 up=0;
        #220 rst=0;
        #50 d=4'b1010;
        #10 ld=1'b1;
        #10 ld=0;
        #400 $finish;
       
    end

    initial begin
        forever begin
          #10 clk= ~clk;
        end
    end


    initial begin
        $monitor("clock=%0d, out=%b, rst=%b, ld=%b, up=%b , d=%b", clk, out,rst,ld,up,d);
    end

    BeCounter bec(out,clk,rst,ld,up,d);

endmodule

cn(mg)/TEMA LAB4/BeCounter.VCD
$date
	Fri Mar 12 18:59:57 2021
$end
$version
	Icarus Verilog
$end
$timescale
	1s
$end
$scope module BeCounter_tb $end
$var wire 4 ! out [3:0] $end
$var reg 1 " clk $end
$var reg 4 # d [3:0] $end
$var reg 1 $ ld $end
$var reg 1 % rst $end
$var reg 1 & up $end
$scope module bec $end
$var wire 1 " clk $end
$var wire 4 ' d [3:0] $end
$var wire 1 $ ld $end
$var wire 4 ( out [3:0] $end
$var wire 1 % rst $end
$var wire 1 & up $end
$var reg 4 ) cnt [3:0] $end
$upscope $end
$upscope $end
$enddefinitions $end
#0
$dumpvars
bx )
bx (
bx '
1&
0%
0$
bx #
0"
bx !
$end
#10
b0 !
b0 (
b0 )
1"
1%
#20
0"
#30
b1 !
b1 (
b1 )
1"
0%
#40
0"
#50
b0 !
b0 (
b0 )
1"
1%
#60
0"
0&
#70
1"
#80
0"
#90
1"
#100
0"
#110
1"
#120
0"
#130
1"
#140
0"
#150
1"
#160
0"
#170
1"
#180
0"
#190
1"
#200
0"
#210
1"
#220
0"
#230
1"
#240
0"
#250
1"
#260
0"
#270
1"
#280
0"
0%
#290
b1111 !
b1111 (
b1111 )
1"
#300
0"
#310
b1110 !
b1110 (
b1110 )
1"
#320
0"
#330
b1101 !
b1101 (
b1101 )
1"
b1010 #
b1010 '
#340
0"
1$
#350
b1100 !
b1100 (
b1100 )
1"
0$
#360
0"
#370
b1011 !
b1011 (
b1011 )
1"
#380
0"
#390
b1010 !
b1010 (
b1010 )
1"
#400
0"
#410
b1001 !
b1001 (
b1001 )
1"
#420
0"
#430
b1000 !
b1000 (
b1000 )
1"
#440
0"
#450
b111 !
b111 (
b111 )
1"
#460
0"
#470
b110 !
b110 (
b110 )
1"
#480
0"
#490
b101 !
b101 (
b101 )
1"
#500
0"
#510
b100 !
b100 (
b100 )
1"
#520
0"
#530
b11 !
b11 (
b11 )
1"
#540
0"
#550
b10 !
b10 (
b10 )
1"
#560
0"
#570
b1 !
b1 (
b1 )
1"
#580
0"
#590
b0 !
b0 (
b0 )
1"
#600
0"
#610
b1111 !
b1111 (
b1111 )
1"
#620
0"
#630
b1110 !
b1110 (
b1110 )
1"
#640
0"
#650
b1101 !
b1101 (
b1101 )
1"
#660
0"
#670
b1100 !
b1100 (
b1100 )
1"
#680
0"
#690
b1011 !
b1011 (
b1011 )
1"
#700
0"
#710
b1010 !
b1010 (
b1010 )
1"
#720
0"
#730
b1001 !
b1001 (
b1001 )
1"
#740
0"
#750
b1000 !
b1000 (
b1000 )
1"
