cn(mg)/TEMA LAB5/BeFA.v
/*
    Implementam un sumator complet folosind modul de design comportamental
    (Co,S) = A + B + Ci
*/

module BeFA(Co, S, A, B, Ci);
    output  [3:0] Co, S;
    input [3:0] A, B, Ci;

    assign {Co, S} = A + B + Ci;
endmodule // BeFA

module BeFA_tb;
    reg [3:0] a, b, ci;
    wire [3:0] co, s;
    initial begin
      $dumpfile("BeFA.vcd");
      $dumpvars(1, a, b, ci, co, s);
      a = 0;
      b = 0;        //  a b c
      ci = 0;       //  0 0 0
      #10 ci = 1;   //  0 0 1
      #10 b = 1;    //  0 1 1
      #10 ci = 0;   //  0 1 0
      #10 a = 1;    //  1 1 0
      #10 ci = 1;   //  1 1 1
      #10 b = 0;    //  1 0 1
      #10 ci = 0;   //  1 0 0

      // inca de 3 ori 

      #10 ci = 1;   //  0 0 1
      #10 b = 1;    //  0 1 1
      #10 ci = 0;   //  0 1 0
      #10 a = 1;    //  1 1 0
      #10 ci = 1;   //  1 1 1
      #10 b = 0;    //  1 0 1
      #10 ci = 0;   //  1 0 0

      #10 ci = 1;   //  0 0 1
      #10 b = 1;    //  0 1 1
      #10 ci = 0;   //  0 1 0
      #10 a = 1;    //  1 1 0
      #10 ci = 1;   //  1 1 1
      #10 b = 0;    //  1 0 1
      #10 ci = 0;   //  1 0 0


      
      #10 $finish;
    end

    BeFA fadd(co, s, a, b, ci);
endmodule // BeFA_tb

cn(mg)/TEMA LAB5/BeFA.vcd
$date
	Wed Mar 24 21:20:39 2021
$end
$version
	Icarus Verilog
$end
$timescale
	1s
$end
$scope module BeFA_tb $end
$var reg 4 ! a [3:0] $end
$upscope $end
$scope module BeFA_tb $end
$var reg 4 " b [3:0] $end
$upscope $end
$scope module BeFA_tb $end
$var reg 4 # ci [3:0] $end
$upscope $end
$scope module BeFA_tb $end
$var wire 4 $ co [3:0] $end
$upscope $end
$scope module BeFA_tb $end
$var wire 4 % s [3:0] $end
$upscope $end
$enddefinitions $end
#0
$dumpvars
b0 %
b0 $
b0 #
b0 "
b0 !
$end
#10
b1 %
b1 #
#20
b10 %
b1 "
#30
b1 %
b0 #
#40
b10 %
b1 !
#50
b11 %
b1 #
#60
b10 %
b0 "
#70
b1 %
b0 #
#80
b10 %
b1 #
#90
b11 %
b1 "
#100
b10 %
b0 #
#120
b11 %
b1 #
#130
b10 %
b0 "
#140
b1 %
b0 #
#150
b10 %
b1 #
#160
b11 %
b1 "
#170
b10 %
b0 #
#190
b11 %
b1 #
#200
b10 %
b0 "
#210
b1 %
b0 #
