cn(mg)/TEMA LAB5/BeFS.v
/*
    Implementam prin modalitatea comporamentala un scazator complet
    {Bo, D} = A - B - Ci
*/

module BeFS(Bo, D, A, B, Bi);
    input [3:0] A, B, Bi;
    output [3:0] Bo, D;

    assign {Bo, D} = A - B - Bi;

endmodule

module BeFS_tb;
    reg [3:0] a, b, bi;
    wire [3:0] bo, d;

    initial begin
      $dumpfile("BeFS.vcd");
      $dumpvars;
      a = 0;
      b = 0;
      bi = 0;       // 0 0 0
      #10 bi = 1;   // 0 0 1
      #10 b = 1;    // 0 1 1
      #10 bi = 0;   // 0 1 0
      #10 a = 1;    // 1 1 0
      #10 bi = 1;   // 1 1 1
      #10 b = 0;    // 1 0 1
      #10 bi = 0;   // 1 0 0
      #10 $finish;
    end

     BeFS sub1(bo, d, a, b, bi);
endmodule // BeFS_tb

cn(mg)/TEMA LAB5/BeFS.vcd
$date
	Wed Mar 24 21:20:44 2021
$end
$version
	Icarus Verilog
$end
$timescale
	1s
$end
$scope module BeFS_tb $end
$var wire 4 ! d [3:0] $end
$var wire 4 " bo [3:0] $end
$var reg 4 # a [3:0] $end
$var reg 4 $ b [3:0] $end
$var reg 4 % bi [3:0] $end
$scope module sub1 $end
$var wire 4 & A [3:0] $end
$var wire 4 ' B [3:0] $end
$var wire 4 ( Bi [3:0] $end
$var wire 4 ) D [3:0] $end
$var wire 4 * Bo [3:0] $end
$upscope $end
$upscope $end
$enddefinitions $end
#0
$dumpvars
b0 *
b0 )
b0 (
b0 '
b0 &
b0 %
b0 $
b0 #
b0 "
b0 !
$end
#10
b1111 !
b1111 )
b1111 "
b1111 *
b1 %
b1 (
#20
b1110 !
b1110 )
b1 $
b1 '
#30
b1111 !
b1111 )
b0 %
b0 (
#40
b0 !
b0 )
b0 "
b0 *
b1 #
b1 &
#50
b1111 !
b1111 )
b1111 "
b1111 *
b1 %
b1 (
#60
b0 !
b0 )
b0 "
b0 *
b0 $
b0 '
#70
b1 !
b1 )
b0 %
b0 (
