cn(mg)/LAB4/StructuralCounter2.v
/*
    L4 E1 Structural Counter

    Vom implementa un bistabil de tip T (FFT) si il vom testa prin implementarea unui numarator
    asincron (Ripple Counter) pe 4 biti.

*/

module FFT(q, qb, clk, rst, d, ld);
    input clk, rst, d, ld;
    output reg q;
    output wire qb;
    assign qb = ~q;
    always @(posedge clk or posedge rst or posedge ld) begin
        if (rst)
            q <= 1'b0;
        else if (ld)
            q <= d;
        else 
            q = ~q;
    end
endmodule // FFT

module RC4(out, clk, rst, d, ld);
    output [3:0] out;
    input clk, rst, ld;
    input [3:0] d;

    wire [3:0] qq;

    FFT t0(out[0], qq[0], clk, rst, d[0], ld);
    FFT t1(out[1], qq[1], out[0], rst, d[1], ld);
    FFT t2(out[2], qq[2], out[1], rst, d[2], ld);
    FFT t3(out[3], qq[3], out[2], rst, d[3], ld);
endmodule //RC4

module RC4_tb;
    wire [3:0] out;
    reg clk, rst, ld;
    reg [3:0] d;

    initial begin
      $dumpfile("RC4.VCD");
      $dumpvars;
      clk = 0;
      rst = 0;
      ld = 0;
      #10 rst = 1;
      #3 rst = 0;
      #280 d = 4'b1011;
      #5 ld = 1;
      #5 ld = 0;
      #500 $finish;
    end

    initial begin
      forever begin
        #10 clk = ~clk;
      end
    end

    RC4 rc(out, clk, rst, d, ld);
endmodule // RC4_tb

/*
module FFT_tb;
    wire [3:0] q, qb;
    reg clk, rst, ld;
    reg [3:0] d;

    initial begin
      $dumpfile("FFT.VCD");
      $dumpvars;
      clk = 0;
      rst = 0;
      ld = 0;
      #10 rst = 1;
      #3 rst = 0;
      #280 d = 4'b1011;
      #5 ld = 1;
      #5 ld = 0;
      #500 $finish;
    end

    // generam semnalul de ceas
    initial begin
        forever begin
          #10 clk = ~clk;
        end  
    end

    FFT t0(q[0], qb[0], clk, rst, d[0], ld);
    FFT t1(q[1], qb[1], q[0], rst, d[1], ld);
    FFT t2(q[2], qb[2], q[1], rst, d[2], ld);
    FFT t3(q[3], qb[3], q[2], rst, d[3], ld);
endmodule // FFT_tb
*/

cn(mg)/LAB4/RC4.VCD
$date
	Thu Mar 11 19:00:30 2021
$end
$version
	Icarus Verilog
$end
$timescale
	1s
$end
$scope module RC4_tb $end
$var wire 4 ! out [3:0] $end
$var reg 1 " clk $end
$var reg 4 # d [3:0] $end
$var reg 1 $ ld $end
$var reg 1 % rst $end
$scope module rc $end
$var wire 1 " clk $end
$var wire 4 & d [3:0] $end
$var wire 1 $ ld $end
$var wire 1 % rst $end
$var wire 4 ' qq [3:0] $end
$var wire 4 ( out [3:0] $end
$scope module t0 $end
$var wire 1 " clk $end
$var wire 1 ) d $end
$var wire 1 $ ld $end
$var wire 1 * qb $end
$var wire 1 % rst $end
$var reg 1 + q $end
$upscope $end
$scope module t1 $end
$var wire 1 , clk $end
$var wire 1 - d $end
$var wire 1 $ ld $end
$var wire 1 . qb $end
$var wire 1 % rst $end
$var reg 1 / q $end
$upscope $end
$scope module t2 $end
$var wire 1 0 clk $end
$var wire 1 1 d $end
$var wire 1 $ ld $end
$var wire 1 2 qb $end
$var wire 1 % rst $end
$var reg 1 3 q $end
$upscope $end
$scope module t3 $end
$var wire 1 4 clk $end
$var wire 1 5 d $end
$var wire 1 $ ld $end
$var wire 1 6 qb $end
$var wire 1 % rst $end
$var reg 1 7 q $end
$upscope $end
$upscope $end
$upscope $end
$enddefinitions $end
#0
$dumpvars
x7
x6
x5
x4
x3
x2
x1
x0
x/
x.
x-
x,
x+
x*
x)
bx (
bx '
bx &
0%
0$
bx #
0"
bx !
$end
#10
1*
0,
1.
00
12
04
b1111 '
16
0+
0/
03
b0 !
b0 (
07
1"
1%
#13
0%
#20
0"
#30
06
17
02
14
13
0.
10
1/
b0 '
0*
1,
b1111 !
b1111 (
1+
1"
#40
0"
#50
b1 '
1*
0,
b1110 !
b1110 (
0+
1"
#60
0"
#70
1.
00
0/
b10 '
0*
1,
b1101 !
b1101 (
1+
1"
#80
0"
#90
b11 '
1*
0,
b1100 !
b1100 (
0+
1"
#100
0"
#110
12
04
03
0.
10
1/
b100 '
0*
1,
b1011 !
b1011 (
1+
1"
#120
0"
#130
b101 '
1*
0,
b1010 !
b1010 (
0+
1"
#140
0"
#150
1.
00
0/
b110 '
0*
1,
b1001 !
b1001 (
1+
1"
#160
0"
#170
b111 '
1*
0,
b1000 !
b1000 (
0+
1"
#180
0"
#190
16
07
02
14
13
0.
10
1/
b1000 '
0*
1,
b111 !
b111 (
1+
1"
#200
0"
#210
b1001 '
1*
0,
b110 !
b110 (
0+
1"
#220
0"
#230
1.
00
0/
b1010 '
0*
1,
b101 !
b101 (
1+
1"
#240
0"
#250
b1011 '
1*
0,
b100 !
b100 (
0+
1"
#260
0"
#270
12
04
03
0.
10
1/
b1100 '
0*
1,
b11 !
b11 (
1+
1"
#280
0"
#290
b1101 '
1*
0,
b10 !
b10 (
0+
1"
#293
1)
1-
01
15
b1011 #
b1011 &
#298
0*
1,
b100 '
06
1+
b1011 !
b1011 (
17
1$
#300
0"
#303
0$
#310
b101 '
1*
0,
b1010 !
b1010 (
0+
1"
#320
0"
#330
1.
00
0/
b110 '
0*
1,
b1001 !
b1001 (
1+
1"
#340
0"
#350
b111 '
1*
0,
b1000 !
b1000 (
0+
1"
#360
0"
#370
16
07
02
14
13
0.
10
1/
b1000 '
0*
1,
b111 !
b111 (
1+
1"
#380
0"
#390
b1001 '
1*
0,
b110 !
b110 (
0+
1"
#400
0"
#410
1.
00
0/
b1010 '
0*
1,
b101 !
b101 (
1+
1"
#420
0"
#430
b1011 '
1*
0,
b100 !
b100 (
0+
1"
#440
0"
#450
12
04
03
0.
10
1/
b1100 '
0*
1,
b11 !
b11 (
1+
1"
#460
0"
#470
b1101 '
1*
0,
b10 !
b10 (
0+
1"
#480
0"
#490
1.
00
0/
b1110 '
0*
1,
b1 !
b1 (
1+
1"
#500
0"
#510
b1111 '
1*
0,
b0 !
b0 (
0+
1"
#520
0"
#530
06
17
02
14
13
0.
10
1/
b0 '
0*
1,
b1111 !
b1111 (
1+
1"
#540
0"
#550
b1 '
1*
0,
b1110 !
b1110 (
0+
1"
#560
0"
#570
1.
00
0/
b10 '
0*
1,
b1101 !
b1101 (
1+
1"
#580
0"
#590
b11 '
1*
0,
b1100 !
b1100 (
0+
1"
#600
0"
#610
12
04
03
0.
10
1/
b100 '
0*
1,
b1011 !
b1011 (
1+
1"
#620
0"
#630
b101 '
1*
0,
b1010 !
b1010 (
0+
1"
#640
0"
#650
1.
00
0/
b110 '
0*
1,
b1001 !
b1001 (
1+
1"
#660
0"
#670
b111 '
1*
0,
b1000 !
b1000 (
0+
1"
#680
0"
#690
16
07
02
14
13
0.
10
1/
b1000 '
0*
1,
b111 !
b111 (
1+
1"
#700
0"
#710
b1001 '
1*
0,
b110 !
b110 (
0+
1"
#720
0"
#730
1.
00
0/
b1010 '
0*
1,
b101 !
b101 (
1+
1"
#740
0"
#750
b1011 '
1*
0,
b100 !
b100 (
0+
1"
#760
0"
#770
12
04
03
0.
10
1/
b1100 '
0*
1,
b11 !
b11 (
1+
1"
#780
0"
#790
b1101 '
1*
0,
b10 !
b10 (
0+
1"
